setup.py
tstore/__init__.py
tstore/pgtablestorage.py
tstore/tstore.py
tstore/utils.py
tstore.egg-info/PKG-INFO
tstore.egg-info/SOURCES.txt
tstore.egg-info/dependency_links.txt
tstore.egg-info/requires.txt
tstore.egg-info/top_level.txt
tstore.egg-info/zip-safe