Metadata-Version: 1.0
Name: tstore
Version: 0.3
Summary: Table-oriented storage
Home-page: https://github.com/langloisjp/tstore
Author: Jean-Philippe Langlois
Author-email: jpl@jplanglois.com
License: MIT
Platform: UNKNOWN
